test_model/__init__.py
test_model/fairness.py
suanfagongpx-0.1.0.dist-info/LICENSE
suanfagongpx-0.1.0.dist-info/METADATA
suanfagongpx-0.1.0.dist-info/WHEEL
suanfagongpx-0.1.0.dist-info/entry_points.txt
suanfagongpx-0.1.0.dist-info/top_level.txt
suanfagongpx-0.1.0.dist-info/RECORD
